py_wordsearch_gen/__init__.py
py_wordsearch_gen/arguments.py
py_wordsearch_gen/consts.py
py_wordsearch_gen/wordsearch.py
py_wordsearch_gen-2025.7.2.dist-info/licenses/LICENSE.md
py_wordsearch_gen-2025.7.2.dist-info/WHEEL
py_wordsearch_gen-2025.7.2.dist-info/entry_points.txt
py_wordsearch_gen-2025.7.2.dist-info/METADATA
py_wordsearch_gen-2025.7.2.dist-info/RECORD
