Metadata-Version: 2.4
Name: py-wordsearch-gen
Version: 2025.7.2
Summary: Command line tool to generate fun to play word searches.
Author: Dan Shernicoff
Author-email: Dan Shernicoff <dan@brassnet.biz>
License-Expression: MIT
License-File: LICENSE.md
Requires-Dist: dykes==0.4.0
Requires-Python: >=3.12
Project-URL: Repository, https://github.com/brass75/wordsearch
Project-URL: homepage, https://github.com/brass75/wordsearch
